Workbook

Sheet Sheet1
A1: Order_ID | B1: Order_Date | C1: Customer | D1: Product | E1: Category | F1: Region | G1: Salesperson | H1: Quantity | I1: Unit_Price | J1: Discount | K1: Payment_Mode | L1: total_sales | M1: discounted_Sales | N1: status
A2: ORD001 | B2: 46054 | C2: Meera | D2: Mouse | E2: Accessories | F2: South | G2: John | H2: 1 | I2: 800 | J2: 0.1 | K2: Cash | L2: =Table1[[#This Row],[Quantity]]*Table1[[#This Row],[Unit_Price]] -> 800 | M2: =Table1[[#This Row],[Quantity]]*Table1[[#This Row],[Unit_Price]]*(1-Table1[[#This Row],[Discount]]) -> 720 | N2: =IF(Table1[[#This Row],[discounted_Sales]]>=50000,"High value","Average") -> Average
A3: ORD002 | B3: 46034 | C3: Meera | D3: Webcam | E3: Accessories | F3: South | G3: Divya | H3: 1 | I3: 3500 | J3: 0 | K3: Cash | L3: =Table1[[#This Row],[Quantity]]*Table1[[#This Row],[Unit_Price]] -> 3500 | M3: =Table1[[#This Row],[Quantity]]*Table1[[#This Row],[Unit_Price]]*(1-Table1[[#This Row],[Discount]]) -> 3500 | N3: =IF(Table1[[#This Row],[discounted_Sales]]>=50000,"High value","Average") -> Average
A4: ORD003 | B4: 46080 | C4: Diya | D4: Monitor | E4: Electronics | F4: East | G4: John | H4: 7 | I4: 12000 | J4: 0.05 | K4: UPI | L4: =Table1[[#This Row],[Quantity]]*Table1[[#This Row],[Unit_Price]] -> 84000 | M4: =Table1[[#This Row],[Quantity]]*Table1[[#This Row],[Unit_Price]]*(1-Table1[[#This Row],[Discount]]) -> 79800 | N4: =IF(Table1[[#This Row],[discounted_Sales]]>=50000,"High value","Average") -> High value
A5: ORD004 | B5: 46042 | C5: Meera | D5: Webcam | E5: Accessories | F5: East | G5: John | H5: 6 | I5: 3500 | J5: 0.1 | K5: Cash | L5: =Table1[[#This Row],[Quantity]]*Table1[[#This Row],[Unit_Price]] -> 21000 | M5: =Table1[[#This Row],[Quantity]]*Table1[[#This Row],[Unit_Price]]*(1-Table1[[#This Row],[Discount]]) -> 18900 | N5: =IF(Table1[[#This Row],[discounted_Sales]]>=50000,"High value","Average") -> Average
A6: ORD005 | B6: 46067 | C6: Diya | D6: Webcam | E6: Accessories | F6: East | G6: John | H6: 2 | I6: 3500 | J6: 0.1 | K6: Net Banking | L6: =Table1[[#This Row],[Quantity]]*Table1[[#This Row],[Unit_Price]] -> 7000 | M6: =Table1[[#This Row],[Quantity]]*Table1[[#This Row],[Unit_Price]]*(1-Table1[[#This Row],[Discount]]) -> 6300 | N6: =IF(Table1[[#This Row],[discounted_Sales]]>=50000,"High value","Average") -> Average
A7: ORD006 | B7: 46093 | C7: Vishnu | D7: Mouse | E7: Accessories | F7: East | G7: Divya | H7: 7 | I7: 800 | J7: 0 | K7: UPI | L7: =Table1[[#This Row],[Quantity]]*Table1[[#This Row],[Unit_Price]] -> 5600 | M7: =Table1[[#This Row],[Quantity]]*Table1[[#This Row],[Unit_Price]]*(1-Table1[[#This Row],[Discount]]) -> 5600 | N7: =IF(Table1[[#This Row],[discounted_Sales]]>=50000,"High value","Average") -> Average
A8: ORD007 | B8: 46060 | C8: Anjali | D8: Mouse | E8: Accessories | F8: South | G8: John | H8: 1 | I8: 800 | J8: 0.05 | K8: Net Banking | L8: =Table1[[#This Row],[Quantity]]*Table1[[#This Row],[Unit_Price]] -> 800 | M8: =Table1[[#This Row],[Quantity]]*Table1[[#This Row],[Unit_Price]]*(1-Table1[[#This Row],[Discount]]) -> 760 | N8: =IF(Table1[[#This Row],[discounted_Sales]]>=50000,"High value","Average") -> Average
A9: ORD008 | B9: 46043 | C9: Fathima | D9: Headset | E9: Accessories | F9: East | G9: Priya | H9: 8 | I9: 2200 | J9: 0.1 | K9: Card | L9: =Table1[[#This Row],[Quantity]]*Table1[[#This Row],[Unit_Price]] -> 17600 | M9: =Table1[[#This Row],[Quantity]]*Table1[[#This Row],[Unit_Price]]*(1-Table1[[#This Row],[Discount]]) -> 15840 | N9: =IF(Table1[[#This Row],[discounted_Sales]]>=50000,"High value","Average") -> Average
A10: ORD009 | B10: 46043 | C10: Sneha | D10: Mouse | E10: Accessories | F10: West | G10: Ameen | H10: 3 | I10: 800 | J10: 0.05 | K10: UPI | L10: =Table1[[#This Row],[Quantity]]*Table1[[#This Row],[Unit_Price]] -> 2400 | M10: =Table1[[#This Row],[Quantity]]*Table1[[#This Row],[Unit_Price]]*(1-Table1[[#This Row],[Discount]]) -> 2280 | N10: =IF(Table1[[#This Row],[discounted_Sales]]>=50000,"High value","Average") -> Average
A11: ORD010 | B11: 46027 | C11: Sanjay | D11: Printer | E11: Electronics | F11: East | G11: Kiran | H11: 1 | I11: 9500 | J11: 0.05 | K11: Card | L11: =Table1[[#This Row],[Quantity]]*Table1[[#This Row],[Unit_Price]] -> 9500 | M11: =Table1[[#This Row],[Quantity]]*Table1[[#This Row],[Unit_Price]]*(1-Table1[[#This Row],[Discount]]) -> 9025 | N11: =IF(Table1[[#This Row],[discounted_Sales]]>=50000,"High value","Average") -> Average
A12: ORD011 | B12: 46050 | C12: Adil | D12: Mouse | E12: Accessories | F12: West | G12: Kiran | H12: 4 | I12: 800 | J12: 0.1 | K12: Net Banking | L12: =Table1[[#This Row],[Quantity]]*Table1[[#This Row],[Unit_Price]] -> 3200 | M12: =Table1[[#This Row],[Quantity]]*Table1[[#This Row],[Unit_Price]]*(1-Table1[[#This Row],[Discount]]) -> 2880 | N12: =IF(Table1[[#This Row],[discounted_Sales]]>=50000,"High value","Average") -> Average
A13: ORD012 | B13: 46054 | C13: Neha | D13: Keyboard | E13: Accessories | F13: East | G13: Divya | H13: 5 | I13: 1500 | J13: 0.05 | K13: Net Banking | L13: =Table1[[#This Row],[Quantity]]*Table1[[#This Row],[Unit_Price]] -> 7500 | M13: =Table1[[#This Row],[Quantity]]*Table1[[#This Row],[Unit_Price]]*(1-Table1[[#This Row],[Discount]]) -> 7125 | N13: =IF(Table1[[#This Row],[discounted_Sales]]>=50000,"High value","Average") -> Average
... A51: ORD050 | B51: 46037 | C51: Riya | D51: Webcam | E51: Accessories | F51: East | G51: Priya | H51: 6 | I51: 3500 | J51: 0 | K51: Card | L51: =Table1[[#This Row],[Quantity]]*Table1[[#This Row],[Unit_Price]] -> 21000 | M51: =Table1[[#This Row],[Quantity]]*Table1[[#This Row],[Unit_Price]]*(1-Table1[[#This Row],[Discount]]) -> 21000 | N51: =IF(Table1[[#This Row],[discounted_Sales]]>=50000,"High value","Average") -> Average

Sheet Sheet3
A1: Product | B1: Category | C1: Unit_Price | D1: Supplier | E1: Stock_Status
A2: Laptop | B2: Electronics | C2: 55000 | D2: TechWorld | E2: In Stock
A3: Mouse | B3: Accessories | C3: 800 | D3: Prime Systems | E3: In Stock
A4: Keyboard | B4: Accessories | C4: 1500 | D4: Smart Traders | E4: In Stock
A5: Monitor | B5: Electronics | C5: 12000 | D5: TechWorld | E5: In Stock
A6: Headset | B6: Accessories | C6: 2200 | D6: Digital Hub | E6: In Stock
A7: Printer | B7: Electronics | C7: 9500 | D7: TechWorld | E7: Low Stock
A8: Webcam | B8: Accessories | C8: 3500 | D8: Prime Systems | E8: In Stock
A9: SSD | B9: Electronics | C9: 6500 | D9: Digital Hub | E9: In Stock

Sheet Sheet2
A1: Task No. | B1: Your Formula / Result
A2: 1 | B2: =SUM(Sheet1!H2:H51) -> 199
A3: 2 | B3: =AVERAGE(Sheet1!I2:I51) -> 8692
A4: 3 | B4: =MAX(Sheet1!I2:I51) -> 55000
A5: 4 | B5: =MIN(Sheet1!I2:I51) -> 800
A6: 5 | B6: =COUNTA(Sheet1!A2:A51) -> 50
A7: 6 | B7: =COUNTIF(Sheet1!K2:K51,"UPI") -> 8
A8: 7 | B8: =SUMIF(Sheet1!F2:F51,"South",Sheet1!H2:H51) -> 28
A9: 8 | B9: =SUMIF(Sheet1!E2:E51,Sheet1!E17,Sheet1!H2:H51) -> 90
A10: 9
A11: 10
A12: 11 | B12: mouse | C12: =LOOKUP(B12,Sheet3!A2:A9,Sheet3!B2:B9) -> Accessories
A13: 12 | B13: mouse | C13: =_xlfn.XLOOKUP(B13,Sheet3!A2:A9,Sheet3!D2:D9) -> Prime Systems
A14: 13 | B14: mouse | C14: =_xlfn.XLOOKUP(B14,Sheet3!A2:A9,Sheet3!E2:E9) -> In Stock
A15: 14
A16: 15 | B16: =SUMIF(Sheet1!G2:G51,"Priya",Sheet1!M2:M51) -> 555530
